pyaiken-0.5.5.dist-info/METADATA
pyaiken-0.5.5.dist-info/WHEEL
pyaiken-0.5.5.dist-info/license_files/LICENSE.txt
pyaiken/__init__.py
pyaiken/pyaiken.cpython-310-aarch64-linux-gnu.so
pyaiken-0.5.5.dist-info/RECORD
