Metadata-Version: 2.1
Name: pyaiken
Version: 0.5.5
Classifier: Programming Language :: Rust
Classifier: Programming Language :: Python :: Implementation :: CPython
Classifier: Development Status :: 3 - Alpha
Classifier: Intended Audience :: Developers
Classifier: Programming Language :: Python :: 3.8
Classifier: Programming Language :: Python :: 3.9
Classifier: Programming Language :: Python :: 3.10
Classifier: Programming Language :: Python :: 3.11
License-File: LICENSE.txt
Summary: Python bindings for aiken
Keywords: python,rust,cardano,smart contract,blockchain
Author: Niels Mündler
Author-email: n.muendler@posteo.de
Maintainer-email: Niels Mündler <n.muendler@posteo.de>
Requires-Python: >=3.7
